<?xml version="1.0"?>

<!--
 | CallerList.xml
 | Overrides for the list of callers 
 -->

<templates>

<template templateClass="org.tpspencer.tal.mvc.sample.model.contact.Contact" >
	<prop name="id" />
	<group>
		<string-prop name="firstName" />
		<string-prop name="lastName" />
	</group>
	<prop name="account" />
	<prop name="company" />
	<member-prop name="address" template="Address" />
	<prop name="previousCrn" />
</template>

<template templateClass="org.tpspencer.tal.mvc.sample.model.common.Address">
	<group name="address">
		<string-prop name="address" maxLength="30" />
		<choice-prop name="town" codeType="townCodeType" unbounded="true" />
		<string-prop name="postCode" format="(GIR 0AA)|((([A-Z-[QVX]][0-9][0-9]?)|(([A-Z-[QVX]][A-Z-[IJZ]][0-9][0-9]?)|(([A-Z-[QVX]][0-9][A-HJKSTUW])|([A-Z-[QVX]][A-Z-[IJZ]][0-9][ABEHMNPRVWXY])))) [0-9][A-Z-[CIKMOV]]{2})" />
		<choice-prop name="country" codeType="countryCodeType" unbounded="false" fieldShowId="true" />
	</group>
</template>

</templates>